creditas/__init__.py
creditas/api_client.py
creditas/configuration.py
creditas/rest.py
creditas/api/__init__.py
creditas/api/account_api.py
creditas/api/administration_api.py
creditas/api/aisp_api.py
creditas/api/authorization_api.py
creditas/api/balance_api.py
creditas/api/card_api.py
creditas/api/cisp_api.py
creditas/api/example_api.py
creditas/api/loan_api.py
creditas/api/payment_api.py
creditas/api/pisp_api.py
creditas/api/statement_api.py
creditas/api/transaction_api.py
creditas/models/__init__.py
creditas/models/account_current.py
creditas/models/account_savings.py
creditas/models/account_statement.py
creditas/models/account_term_deposit.py
creditas/models/account_transaction.py
creditas/models/account_transaction_filter.py
creditas/models/account_transaction_filter_partner_account.py
creditas/models/account_transaction_partner_account.py
creditas/models/aisp_account.py
creditas/models/aisp_account_transaction.py
creditas/models/aisp_account_transaction_partner_account.py
creditas/models/body.py
creditas/models/body1.py
creditas/models/body10.py
creditas/models/body11.py
creditas/models/body12.py
creditas/models/body13.py
creditas/models/body14.py
creditas/models/body15.py
creditas/models/body16.py
creditas/models/body17.py
creditas/models/body18.py
creditas/models/body19.py
creditas/models/body2.py
creditas/models/body20.py
creditas/models/body21.py
creditas/models/body22.py
creditas/models/body23.py
creditas/models/body24.py
creditas/models/body25.py
creditas/models/body26.py
creditas/models/body27.py
creditas/models/body28.py
creditas/models/body3.py
creditas/models/body4.py
creditas/models/body5.py
creditas/models/body6.py
creditas/models/body7.py
creditas/models/body8.py
creditas/models/body9.py
creditas/models/cispaccountbalancecheck_card.py
creditas/models/clientregistrationcreate_client_application.py
creditas/models/debit_card.py
creditas/models/error_basic.py
creditas/models/error_transaction_authorization.py
creditas-1.0.0.1.dist-info/LICENSE
creditas-1.0.0.1.dist-info/METADATA
creditas-1.0.0.1.dist-info/WHEEL
creditas-1.0.0.1.dist-info/top_level.txt
creditas-1.0.0.1.dist-info/RECORD
